amsaf/AffineParameterMapGenerator.py
amsaf/AmsafExecutor.py
amsaf/AmsafImageFilter.py
amsaf/BSplineParameterMapGenerator.py
amsaf/ParameterMapGenerator.py
amsaf/ParameterMapService.py
amsaf/RigidParameterMapGenerator.py
amsaf/__init__.py
hart_amsaf-0.0.4.dist-info/DESCRIPTION.rst
hart_amsaf-0.0.4.dist-info/METADATA
hart_amsaf-0.0.4.dist-info/RECORD
hart_amsaf-0.0.4.dist-info/WHEEL
hart_amsaf-0.0.4.dist-info/metadata.json
hart_amsaf-0.0.4.dist-info/top_level.txt
