Metadata-Version: 2.0
Name: hart-amsaf
Version: 0.0.4
Summary: The HART Lab Automated MRI Segmentation and Analysis Framework
Home-page: https://github.com/iancmcdonald/AMSAF
Author: Ian McDonald and Daniel Ho
Author-email: ian.c.mcdonald@berkeley.edu
License: MIT
Keywords: hart,hart-amsaf,HartAmsaf,amsaf,segmentation,mri,medical
Platform: UNKNOWN
Requires-Dist: scipy
Requires-Dist: numpy
Requires-Dist: scikit-learn
